waifuboard/__init__.py
waifuboard/booru.py
waifuboard/danbooru.py
waifuboard/moebooru.py
waifuboard/safebooru.py
waifuboard/utils.py
waifuboard-0.1.10.dist-info/licenses/LICENSE
waifuboard-0.1.10.dist-info/METADATA
waifuboard-0.1.10.dist-info/WHEEL
waifuboard-0.1.10.dist-info/top_level.txt
waifuboard-0.1.10.dist-info/RECORD
