Metadata-Version: 2.4
Name: waifuboard
Version: 0.1.10
Summary: Asynchronous API for downloading images, tags, and metadata from image board sites (e.g., Danbooru, Safebooru, Yandere). Ignore the downloaded files.
Author-email: ChijiangZhai <chijiangzhai@gmail.com>
Maintainer-email: ChijiangZhai <chijiangzhai@gmail.com>
License:                   GNU LESSER GENERAL PUBLIC LICENSE
Project-URL: Homepage, https://github.com/2513502304/WaifuBoard
Project-URL: Repository, https://github.com/2513502304/WaifuBoard.git
Project-URL: Issues, https://github.com/2513502304/WaifuBoard/issues
Keywords: python,acg,crawler,spider,ai,imageboard,images,tags,metadata
Classifier: Development Status :: 3 - Alpha
Classifier: Intended Audience :: Developers
Classifier: License :: OSI Approved :: GNU Lesser General Public License v2 or later (LGPLv2+)
Classifier: Operating System :: OS Independent
Classifier: Programming Language :: Python :: 3
Classifier: Programming Language :: Python :: 3 :: Only
Classifier: Programming Language :: Python :: 3.9
Classifier: Programming Language :: Python :: 3.10
Classifier: Programming Language :: Python :: 3.11
Classifier: Programming Language :: Python :: 3.12
Classifier: Programming Language :: Python :: 3.13
Classifier: Programming Language :: Python :: 3.14
Classifier: Programming Language :: Python :: 3.15
Classifier: Topic :: Internet
Requires-Python: >=3.9
License-File: LICENSE
Requires-Dist: aiofiles>=24.1.0
Requires-Dist: fake-useragent>=1.2.1
Requires-Dist: httpx[http2]>=0.28.1
Requires-Dist: orjson>=3.11.5
Requires-Dist: pandas>=2.3.1
Requires-Dist: parsel>=1.10.0
Requires-Dist: rich>=14.1.0
Requires-Dist: tenacity>=9.1.2
Dynamic: license-file
